miniecs_test_package/__init__.py
miniecs_test_package/example.py
miniecs_test_package/miniecs.py
miniecs_test_package_Jeremias_V-0.0.21.dist-info/LICENSE
miniecs_test_package_Jeremias_V-0.0.21.dist-info/METADATA
miniecs_test_package_Jeremias_V-0.0.21.dist-info/WHEEL
miniecs_test_package_Jeremias_V-0.0.21.dist-info/top_level.txt
miniecs_test_package_Jeremias_V-0.0.21.dist-info/RECORD
