Metadata-Version: 2.1
Name: miniecs_test_package-Jeremias-V
Version: 0.0.21
Summary: A small package for operating systems course.
Home-page: https://github.com/Jeremias-V
Author: Jeremias-V
Author-email: jeremias.villalobos.t@gmail.com
License: UNKNOWN
Platform: UNKNOWN
Classifier: Programming Language :: Python :: 3
Classifier: License :: OSI Approved :: MIT License
Classifier: Operating System :: POSIX :: Linux
Requires-Python: >=3.6
License-File: LICENSE
